{
  "settingsVersion": "1.8.01",
  "makeOfflineCompatible": false,
  "inlineAssets": false,
  "includePluginCSS": "",
  "includeSvelteCSS": true,
  "titleProperty": "PhD Studies Thomas Davies",
  "customHeadContentPath": "",
  "faviconPath": "",
  "documentWidth": "60em",
  "sidebarWidth": "20em",
  "minOutlineCollapse": 2,
  "startOutlineCollapsed": false,
  "allowFoldingHeadings": true,
  "allowFoldingLists": true,
  "allowResizingSidebars": true,
  "logLevel": "warning",
  "minifyHTML": true,
  "makeNamesWebStyle": true,
  "onlyExportModified": true,
  "deleteOldFiles": true,
  "addThemeToggle": true,
  "addOutline": true,
  "addFileNav": true,
  "addSearchBar": true,
  "addGraphView": true,
  "addTitle": true,
  "addRSSFeed": true,
  "siteURL": "https://www.staff.hs-mittweida.de/~davies/intranet/",
  "authorName": "Thomas Davies",
  "vaultTitle": "PhD Studies",
  "exportPreset": "website",
  "openAfterExport": true,
  "graphAttractionForce": 1,
  "graphLinkLength": 10,
  "graphRepulsionForce": 150,
  "graphCentralForce": 3,
  "graphEdgePruning": 100,
  "graphMinNodeSize": 3,
  "graphMaxNodeSize": 7,
  "showDefaultTreeIcons": false,
  "emojiStyle": "Native",
  "defaultFileIcon": "lucide//file",
  "defaultFolderIcon": "lucide//folder",
  "defaultMediaIcon": "lucide//file-image",
  "exportPath": "/home/thomas/Documents/",
  "filesToExport": [
    [
      "Lehre/Kryptologie/Diagrams",
      "Lehre/Kryptologie/Figures",
      "Lehre/Kryptologie/0 - Inhaltsverzeichnis.md",
      "Lehre/Kryptologie/1 -  Einführung.md",
      "Lehre/Kryptologie/2 - Algebraische und Zahlentheoretische Grundlagen (1).md",
      "Lehre/Kryptologie/3 - RSA (Rivest Shamir Adleman).md",
      "Lehre/Kryptologie/4 - Angriffe auf RSA.md",
      "Lehre/Kryptologie/5 - Rabin Verfahren.md",
      "Lehre/Kryptologie/6 - Angriffe auf das Rabin-Verfahren.md",
      "Lehre/Kryptologie/7 - Algebraische und Zahlentheoretische Grundlagen (2).md",
      "Lehre/Kryptologie/8 - No-Key Protokolle.md",
      "Lehre/Kryptologie/9 - El Gamal's Kryptosystem.md",
      "Lehre/Kryptologie/10 - Angriffe auf die El Gamal Signatur.md",
      "Lehre/Kryptologie/11 - Homomorphe Verschlüsselung.md",
      "Lehre/Kryptologie/12 - Elliptische Kurven.md",
      "Lehre/Kryptologie/A - Sage Funktionen.md",
      "Lehre/Kryptologie/Vorlesungsfortschritt WS2024_25.md",
      "Lehre/Kryptologie/X - Zusatz Mathematik (Informativ).md",
      "ML Programming",
      "PDFs",
      "PhD Studies",
      "References",
      "index.md"
    ]
  ]
}